gaboon/__init__.py
gaboon/__main__.py
gaboon/_sys_path_and_config_setup.py
gaboon/boa_tools.py
gaboon/config.py
gaboon/gaboon_account.py
gaboon/logging.py
gaboon/commands/__init__.py
gaboon/commands/compile.py
gaboon/commands/config_.py
gaboon/commands/console.py
gaboon/commands/init.py
gaboon/commands/install.py
gaboon/commands/purge.py
gaboon/commands/run.py
gaboon/commands/test.py
gaboon/commands/wallet.py
gaboon/constants/file_data.py
gaboon/constants/vars.py
gaboon_cli-0.1.2.dist-info/METADATA
gaboon_cli-0.1.2.dist-info/WHEEL
gaboon_cli-0.1.2.dist-info/entry_points.txt
gaboon_cli-0.1.2.dist-info/licenses/LICENCE-APACHE
gaboon_cli-0.1.2.dist-info/licenses/LICENCE-MIT
gaboon_cli-0.1.2.dist-info/RECORD
