Metadata-Version: 2.3
Name: gaboon-cli
Version: 0.1.2
Summary: Pythonic smart contract development framework using Titanoboa
Author-email: PatrickAlphac <54278053+PatrickAlphaC@users.noreply.github.com>, charles-cooper <3867501+charles-cooper@users.noreply.github.com>
License-File: LICENCE-APACHE
License-File: LICENCE-MIT
Requires-Python: <3.13,>=3.11
Requires-Dist: python-dotenv>=1.0.1
Requires-Dist: titanoboa-zksync>=v0.2.2
Requires-Dist: titanoboa>=0.2.2
Requires-Dist: tomli-w>=1.0.0
Requires-Dist: tomlkit>=0.13.2
Requires-Dist: tqdm>=4.66.5
Provides-Extra: docs
Requires-Dist: shibuya>=2024.8.30; extra == 'docs'
Requires-Dist: sphinx-argparse>=0.5.2; extra == 'docs'
Requires-Dist: sphinx-copybutton>=0.5.2; extra == 'docs'
Requires-Dist: sphinx-multiversion>=0.2.4; extra == 'docs'
Requires-Dist: sphinx>=8.0.2; extra == 'docs'
